orchestra/Dockerfile
orchestra/__init__.py
orchestra/backend/__init__.py
orchestra/backend/mcp_server.py
orchestra/backend/monitor.py
orchestra/frontend/__init__.py
orchestra/frontend/app.py
orchestra/frontend/state.py
orchestra/frontend/widgets/__init__.py
orchestra/frontend/widgets/diff_tab.py
orchestra/frontend/widgets/hud.py
orchestra/frontend/widgets/messages_tab.py
orchestra/lib/__init__.py
orchestra/lib/agent_protocol.py
orchestra/lib/config.py
orchestra/lib/file_watcher.py
orchestra/lib/logger.py
orchestra/lib/message.py
orchestra/lib/monitor.py
orchestra/lib/prompts.py
orchestra/lib/sessions.py
orchestra/lib/tmux_protocol.py
orchestra/runners/__init__.py
orchestra/runners/hook_monitor.py
orchestra/runners/launch.py
orchestra/runners/maestro.py
orchestra/runners/orchestra-hook-forward.sh
orchestra/runners/setup.py
orchestra_code-0.2.1.dist-info/licenses/LICENSE
orchestra_code-0.2.1.dist-info/METADATA
orchestra_code-0.2.1.dist-info/WHEEL
orchestra_code-0.2.1.dist-info/entry_points.txt
orchestra_code-0.2.1.dist-info/top_level.txt
orchestra_code-0.2.1.dist-info/RECORD
